Metadata-Version: 1.0
Name: sb-distributions
Version: 0.1
Summary: Gaussian and binomial distributions
Home-page: UNKNOWN
Author: Sergio Beltran
Author-email: engsergiobeltran@gmail.com
License: UNKNOWN
Platform: UNKNOWN
